dh_backtest/__init__.py
dh_backtest/backtest_engine.py
dh_backtest/main.py
dh_backtest/models/__init__.py
dh_backtest/models/data_classes.py
dh_backtest/models/local_data.py
dh_backtest/models/remote_data.py
dh_backtest/views/__init__.py
dh_backtest/views/css.py
dh_backtest/views/view_bt_result.py
dh_backtest/views/view_bt_result_mp.py
dh_backtest-0.1.17.dist-info/METADATA
dh_backtest-0.1.17.dist-info/WHEEL
dh_backtest-0.1.17.dist-info/top_level.txt
dh_backtest-0.1.17.dist-info/RECORD
