Metadata-Version: 2.1
Name: dh_backtest
Version: 0.1.17
Requires-Dist: arrow>=1.3.0
Requires-Dist: dash>=2.17.1
Requires-Dist: dash-bootstrap-components>=1.6.0
Requires-Dist: futu-api>=8.5.4508
Requires-Dist: ib-insync>=0.9.86
Requires-Dist: numpy>=2.1.1
Requires-Dist: pandas>=2.2.2
Requires-Dist: plotly>=5.23.0
Requires-Dist: python-dateutil>=2.9.0.post0
Requires-Dist: pytz>=2024.1
Requires-Dist: termcolor>=2.4.0
